Metadata-Version: 2.1
Name: tadtool
Version: 0.83
Summary: Assistant to find cutoffs in TAD calling algorithms.
Home-page: https://github.com/vaquerizaslab/tadtool
Author: Vaquerizas lab
Author-email: kai.kruse@mpi-muenster.mpg.de
License: UNKNOWN
Download-URL: https://github.com/vaquerizaslab/tadtool/tarball/0.81
Keywords: bioinformatics,hi-c,genomics,tad
Platform: UNKNOWN
License-File: LICENSE
